dkinst/__init__.py
dkinst/cli.py
dkinst/config.toml
dkinst/installers/__init__.py
dkinst/installers/_base.py
dkinst/installers/bashdb.py
dkinst/installers/brew.py
dkinst/installers/chocolatey.py
dkinst/installers/clamav.py
dkinst/installers/crowdsec.py
dkinst/installers/docker.py
dkinst/installers/elastickibana.py
dkinst/installers/elasticsearch.py
dkinst/installers/eset_internet_security.py
dkinst/installers/ffmpeg.py
dkinst/installers/fibratus.py
dkinst/installers/git.py
dkinst/installers/google_chrome.py
dkinst/installers/krusader.py
dkinst/installers/mongodb.py
dkinst/installers/nodejs.py
dkinst/installers/notepadpp.py
dkinst/installers/npcap.py
dkinst/installers/orca.py
dkinst/installers/pbtk.py
dkinst/installers/pycharm.py
dkinst/installers/python.py
dkinst/installers/pywintrace.py
dkinst/installers/qbittorrent.py
dkinst/installers/rdp_gpu.py
dkinst/installers/robocorp.py
dkinst/installers/rufus.py
dkinst/installers/tesseract_ocr.py
dkinst/installers/total_commander.py
dkinst/installers/virtual_keyboard.py
dkinst/installers/vlc.py
dkinst/installers/vmware_tools.py
dkinst/installers/vs_build_tools_2022.py
dkinst/installers/winget.py
dkinst/installers/wsl.py
dkinst/installers/xrdp.py
dkinst/installers/helpers/__init__.py
dkinst/installers/helpers/chocolatey_installer.py
dkinst/installers/helpers/clamav_installer.py
dkinst/installers/helpers/crowdsec_installer.py
dkinst/installers/helpers/docker_installer.py
dkinst/installers/helpers/elastic_manager.py
dkinst/installers/helpers/eset_installer.py
dkinst/installers/helpers/ffmpeg_manager.py
dkinst/installers/helpers/mongodb_installer.py
dkinst/installers/helpers/nodejs_installer.py
dkinst/installers/helpers/npcap_installer.py
dkinst/installers/helpers/pycharm_installer.py
dkinst/installers/helpers/rdp_gpu_manager.py
dkinst/installers/helpers/tesseract_ocr_manager.py
dkinst/installers/helpers/vs_build_tools_installer.py
dkinst/installers/helpers/winget_installer.py
dkinst/installers/helpers/wsl_manager.py
dkinst-0.38.1.dist-info/licenses/LICENSE
dkinst-0.38.1.dist-info/METADATA
dkinst-0.38.1.dist-info/WHEEL
dkinst-0.38.1.dist-info/entry_points.txt
dkinst-0.38.1.dist-info/top_level.txt
dkinst-0.38.1.dist-info/RECORD
