Metadata-Version: 2.4
Name: dkinst
Version: 0.38.1
Summary: Den K Simple Installer
Author: Denis Kras
License-Expression: MIT
Project-URL: Homepage, https://github.com/denis-kras/dkinst
Classifier: Intended Audience :: Developers
Classifier: Programming Language :: Python :: 3
Classifier: Topic :: Software Development :: Libraries :: Python Modules
Requires-Python: >=3.12
License-File: LICENSE
Requires-Dist: wheel
Requires-Dist: argcomplete==3.6.3
Requires-Dist: langcodes==3.5.1
Requires-Dist: language-data==1.4.0
Requires-Dist: prompt_toolkit==3.0.52
Requires-Dist: psutil==7.1.3
Requires-Dist: rich==14.2.0
Requires-Dist: atomicshop
Dynamic: license-file
